{"commitInfo":{"timestamp":1782790359347,"operation":"WRITE","operationParameters":{"mode":"Overwrite","partitionBy":"[]"},"isolationLevel":"Serializable","isBlindAppend":false,"operationMetrics":{"numFiles":"1","numOutputRows":"92","numOutputBytes":"3896"},"engineInfo":"Apache-Spark/3.5.3 Delta-Lake/3.0.0","txnId":"714eb88a-322d-488e-b406-9af3eed8ebef"}}
{"metaData":{"id":"fb3022c0-3501-4b29-84f8-8b7395a2383b","format":{"provider":"parquet","options":{}},"schemaString":"{\"type\":\"struct\",\"fields\":[{\"name\":\"trend_date\",\"type\":\"date\",\"nullable\":true,\"metadata\":{}},{\"name\":\"category\",\"type\":\"string\",\"nullable\":true,\"metadata\":{}},{\"name\":\"daily_sales\",\"type\":\"double\",\"nullable\":true,\"metadata\":{}},{\"name\":\"daily_quantity\",\"type\":\"long\",\"nullable\":true,\"metadata\":{}},{\"name\":\"moving_avg_7_days\",\"type\":\"double\",\"nullable\":true,\"metadata\":{}},{\"name\":\"_updated_at\",\"type\":\"timestamp\",\"nullable\":true,\"metadata\":{}},{\"name\":\"_load_date\",\"type\":\"string\",\"nullable\":true,\"metadata\":{}}]}","partitionColumns":[],"configuration":{},"createdTime":1782790357378}}
{"protocol":{"minReaderVersion":1,"minWriterVersion":2}}
{"add":{"path":"part-00000-8b903afe-3672-4ab6-8289-f1e13e829741-c000.snappy.parquet","partitionValues":{},"size":3896,"modificationTime":1782790359176,"dataChange":true,"stats":"{\"numRecords\":92,\"minValues\":{\"trend_date\":\"2026-04-01\",\"category\":\"Beauty\",\"daily_sales\":38.14,\"daily_quantity\":1,\"moving_avg_7_days\":54.9,\"_updated_at\":\"2026-06-30T03:32:37.453Z\",\"_load_date\":\"2026-06-30\"},\"maxValues\":{\"trend_date\":\"2026-06-28\",\"category\":\"Sports\",\"daily_sales\":2194.6000000000004,\"daily_quantity\":10,\"moving_avg_7_days\":2194.6,\"_updated_at\":\"2026-06-30T03:32:37.453Z\",\"_load_date\":\"2026-06-30\"},\"nullCount\":{\"trend_date\":0,\"category\":0,\"daily_sales\":0,\"daily_quantity\":0,\"moving_avg_7_days\":0,\"_updated_at\":0,\"_load_date\":0}}"}}
